{
  "name": "CardTypes",
  "fields": [
    {
      "fieldName": "name",
      "fieldType": "String"
    },
    {
      "fieldName": "issuerId",
      "fieldType": "Long"
    },
    {
      "fieldName": "modifiedDate",
      "fieldType": "Instant"
    }
  ],
  "relationships": [],
  "changelogDate": "20200617161604",
  "entityTableName": "card_types",
  "dto": "mapstruct",
  "pagination": "no",
  "service": "serviceImpl",
  "jpaMetamodelFiltering": true,
  "fluentMethods": true,
  "readOnly": false,
  "embedded": false,
  "clientRootFolder": "vscommerce",
  "applications": "*",
  "microserviceName": "vscommerce"
}
